Metadata-Version: 2.1
Name: pdftext-to-speech
Version: 1.1
Summary: A Python package for converting PDF and TXT files to audio
Home-page: https://github.com/danysrour/textToSpeech
Author: Dany Srour
Author-email: dany.srour@gmail.com
Classifier: Development Status :: 5 - Production/Stable
Classifier: Intended Audience :: Developers
Classifier: License :: OSI Approved :: MIT License
Classifier: Operating System :: OS Independent
Classifier: Programming Language :: Python :: 3
Classifier: Programming Language :: Python :: 3.7
Classifier: Programming Language :: Python :: 3.8
Classifier: Programming Language :: Python :: 3.9
Requires-Python: >=3.7
License-File: LICENSE.txt
